nomad/__init__.py
nomad/command.py
nomad/config.py
nomad/constants.py
nomad/divider.py
nomad/entrypoints.py
nomad/infras.py
nomad/main.py
nomad/nomad_logger.py
nomad/ui.py
nomad/utils.py
nomad/agents/__init__.py
nomad/agents/base.py
nomad/agents/ec2.py
nomad/agents/meta.py
nomad/agents/scripts/__init__.py
nomad/agents/scripts/docker/Dockerfile
nomad/agents/scripts/docker/ec2/apply.sh
nomad/agents/scripts/docker/ec2/run.sh
nomad/agents/scripts/ec2/apply.sh
nomad/agents/scripts/ec2/run.sh
nomad/examples/__init__.py
nomad/examples/ec2/additional_paths.yml
nomad/examples/ec2/basic_function.yml
nomad/examples/ec2/basic_jupyter.yml
nomad/examples/ec2/basic_project.yml
nomad/examples/ec2/basic_script.yml
nomad/examples/ec2/download_files.yml
nomad/examples/ec2/env_vars.yml
nomad/examples/ec2/matrix.yml
nomad/images/__init__.py
nomad/images/docker_image.py
nomad/images/meta.py
nomad/images/registries.py
nomad/parsers/yml.py
nomad/tasks/__init__.py
nomad/tasks/apply.py
nomad/tasks/base.py
nomad/tasks/build.py
nomad/tasks/delete.py
nomad/tasks/init.py
nomad/tasks/run.py
nomad/templates/__init__.py
nomad/templates/common.yml
nomad/templates/entrypoints/function.yml
nomad/templates/entrypoints/jupyter.yml
nomad/templates/entrypoints/project.yml
nomad/templates/entrypoints/script.yml
nomad/templates/infra/ec2-docker.yml
nomad/templates/infra/ec2.yml
nomad/tests/test_base_task.py
nomad/tests/test_entrypoint.py
nomad/tests/test_infras.py
nomad/tests/test_init.py
nomad/tests/test_utils.py
nomad/tests/test_yml_parser.py
nomad/tests/confs/bad_additional_paths.yml
nomad/tests/confs/bad_entrypoint.yml
nomad/tests/confs/bad_env.yml
nomad/tests/confs/bad_python_version_format.yml
nomad/tests/confs/bad_requirements.yml
nomad/tests/confs/infra_bad_type.yml
nomad/tests/confs/infra_no_type.yml
nomad/tests/confs/no_entrypoint.yml
nomad/tests/confs/no_infra.yml
nomad/tests/confs/normal_conf.yml
nomad/tests/confs/normal_conf_jupyter.yml
nomad/tests/confs/python_major.yml
nomad_dev-0.0.5.dist-info/LICENSE
nomad_dev-0.0.5.dist-info/METADATA
nomad_dev-0.0.5.dist-info/WHEEL
nomad_dev-0.0.5.dist-info/entry_points.txt
nomad_dev-0.0.5.dist-info/top_level.txt
nomad_dev-0.0.5.dist-info/RECORD
