Metadata-Version: 2.1
Name: nomad-dev
Version: 0.0.5
Summary: Run any code on the cloud, instantly.
Author: prism founders
Author-email: hello@runprism.com
License: Apache-2.0
Platform: unix
Platform: linux
Platform: osx
Platform: win32
Classifier: Programming Language :: Python :: 3
Classifier: Programming Language :: Python :: 3.8
Classifier: Programming Language :: Python :: 3.9
Classifier: Programming Language :: Python :: 3.10
Classifier: Programming Language :: Python :: 3.11
Requires-Python: >=3.8
License-File: LICENSE
Requires-Dist: astor >=0.7
Requires-Dist: boto3 >=1
Requires-Dist: botocore >=1
Requires-Dist: click >=8
Requires-Dist: PyYAML >=6
Requires-Dist: requests >=2
Requires-Dist: Jinja2 ==3.1.2
Requires-Dist: MarkupSafe >=2.0
Requires-Dist: coolname >=2.2
Requires-Dist: shortuuid >=1.0
Requires-Dist: rich-click >=1.6.1
Requires-Dist: beautifulsoup4 >=4.12
Provides-Extra: docker
Requires-Dist: docker >=6.1 ; extra == 'docker'
Provides-Extra: jupyter
Requires-Dist: papermill ; extra == 'jupyter'
Provides-Extra: testing
Requires-Dist: pytest >=7 ; extra == 'testing'
Requires-Dist: build >=0.10 ; extra == 'testing'
Requires-Dist: twine >=4.0 ; extra == 'testing'
